Workbook
Name Orders: #REF!
Name People: #REF!
Name Returns: #REF!

Sheet Pivot_Region_Sales
A3: Row Labels | B3: Sum of Sales
A4: West | B4: 739813.61
A5: East | B5: 691828.17
A6: Central | B6: 503170.67
A7: South | B7: 391721.91
A8: Grand Total | B8: 2326534.4

Sheet Pivot_Category_Sales
A3: Row Labels | B3: Sum of Sales
A4: Technology | B4: 839893.28
A5: Furniture | B5: 754747.76
A6: Office Supplies | B6: 731893.31
A7: Grand Total | B7: 2326534.4

Sheet Pivot_ShipMode_Orders
A3: Row Labels | B3: Count of Order ID
A4: Standard Class | B4: 6120
A5: Second Class | B5: 1979
A6: First Class | B6: 1548
A7: Same Day | B7: 547
A8: Grand Total | B8: 10194

Sheet Pivot_Segment_Sales
A3: Row Labels | B3: Sum of Sales
A4: Consumer | B4: 1170659.8
A5: Corporate | B5: 715806.13
A6: Home Office | B6: 440068.43
A7: Grand Total | B7: 2326534.4

Sheet Pivot_Monthly_Sales
A3: Row Labels | B3: Sum of Sales
A4: ноя | B4: 352665.99
A5: дек | B5: 330218.18
A6: сен | B6: 308883.67
A7: мар | B7: 210672.09
A8: окт | B8: 207126.26
A9: авг | B9: 161821.91
A10: май | B10: 158765.03
A11: июн | B11: 153460
A12: июл | B12: 149001.71
A13: апр | B13: 138098.75
A14: янв | B14: 96069.516
A15: фев | B15: 59751.251
A16: Grand Total | B16: 2326534.4

Sheet Orders
A1: Row ID | B1: Order ID | C1: Order Date | D1: Ship Date | E1: Ship Mode | F1: Customer ID | G1: Customer Name | H1: Segment | I1: Country/Region | J1: City | K1: State/Province | L1: Fixed_Postal | M1: Region | N1: Product ID | O1: Category | P1: Sub-Category | Q1: Product Name | R1: Sales | S1: Quantity | T1: Discount | U1: Profit | W1: Regional Manager | Y1: Profit_Status | AB1: SUMIFS(west) | AC1: SUMIFS(central) | AD1: SUMIFS(south) | AE1: SUMIFS(east) | AF1: COUNTIFS(west) | AG1: COUNTIFS(central) | AH1: COUNTIFS(south) | AI1: COUNTIFS(east)
A2: 1 | B2: US-2023-103800 | C2: 44929 | D2: 44933 | E2: Standard Class | F2: DP-13000 | G2: Darren Powers | H2: Consumer | I2: United States | J2: Houston | K2: Texas | L2: 77095 | M2: Central | N2: OFF-PA-10000174 | O2: Office Supplies | P2: Paper | Q2: Message Book, Wirebound, Four 5 1/2" X 4" Forms/Pg., 200 Dupl. Sets/Book | R2: 16.448 | S2: 2 | T2: 0.2 | U2: 5.5512 | W2: =INDEX(People!A:A,MATCH(M2,People!B:B,0)) -> Roxanne Rodriguez | Y2: =IF(U2<0,"Zərər",IF(U2<100,"Aşağı Qazanc","Yüksək Qazanc")) -> Aşağı Qazanc | AB2: =SUMIFS(R:R,M:M,"West",O:O,"Furniture") -> 260679.73 | AC2: =SUMIFS(R:R, M:M, "Central", O:O, "Furniture") -> 164537.65 | AD2: =SUMIFS(R:R, M:M,"South", O:O, "Furniture") -> 117298.68 | AE2: =SUMIFS(R:R,M:M,"East",O:O,"Furniture") -> 212231.7 | AF2: =COUNTIFS(M:M,"West",U:U,"<0") -> 321 | AG2: =COUNTIFS(M:M,"Central",U:U,"<0") -> 747 | AH2: =COUNTIFS(M:M,"South",U:U,"<0") -> 259 | AI2: =COUNTIFS(M:M,"East",U:U,"<0") -> 574
A3: =A2+1 -> 2 | B3: US-2023-112326 | C3: 44930 | D3: 44934 | E3: Standard Class | F3: PO-19195 | G3: Phillina Ober | H3: Home Office | I3: United States | J3: Naperville | K3: Illinois | L3: 60540 | M3: Central | N3: OFF-BI-10004094 | O3: Office Supplies | P3: Binders | Q3: GBC Standard Plastic Binding Systems Combs | R3: 3.54 | S3: 2 | T3: 0.8 | U3: -5.487 | W3: =INDEX(People!A:A,MATCH(M3,People!B:B,0)) -> Roxanne Rodriguez | Y3: =IF(U3<0,"Zərər",IF(U3<100,"Aşağı Qazanc","Yüksək Qazanc")) -> Zərər
A4: =A3+1 -> 3 | B4: US-2023-112326 | C4: 44930 | D4: 44934 | E4: Standard Class | F4: PO-19195 | G4: Phillina Ober | H4: Home Office | I4: United States | J4: Naperville | K4: Illinois | L4: 60540 | M4: Central | N4: OFF-LA-10003223 | O4: Office Supplies | P4: Labels | Q4: Avery 508 | R4: 11.784 | S4: 3 | T4: 0.2 | U4: 4.2717 | W4: =INDEX(People!A:A,MATCH(M4,People!B:B,0)) -> Roxanne Rodriguez | Y4: =IF(U4<0,"Zərər",IF(U4<100,"Aşağı Qazanc","Yüksək Qazanc")) -> Aşağı Qazanc
A5: =A4+1 -> 4 | B5: US-2023-112326 | C5: 44930 | D5: 44934 | E5: Standard Class | F5: PO-19195 | G5: Phillina Ober | H5: Home Office | I5: United States | J5: Naperville | K5: Illinois | L5: 60540 | M5: Central | N5: OFF-ST-10002743 | O5: Office Supplies | P5: Storage | Q5: SAFCO Boltless Steel Shelving | R5: 272.736 | S5: 3 | T5: 0.2 | U5: -64.7748 | W5: =INDEX(People!A:A,MATCH(M5,People!B:B,0)) -> Roxanne Rodriguez | Y5: =IF(U5<0,"Zərər",IF(U5<100,"Aşağı Qazanc","Yüksək Qazanc")) -> Zərər
A6: =A5+1 -> 5 | B6: US-2023-141817 | C6: 44931 | D6: 44938 | E6: Standard Class | F6: MB-18085 | G6: Mick Brown | H6: Consumer | I6: United States | J6: Philadelphia | K6: Pennsylvania | L6: 19143 | M6: East | N6: OFF-AR-10003478 | O6: Office Supplies | P6: Art | Q6: Avery Hi-Liter EverBold Pen Style Fluorescent Highlighters, 4/Pack | R6: 19.536 | S6: 3 | T6: 0.2 | U6: 4.884 | W6: =INDEX(People!A:A,MATCH(M6,People!B:B,0)) -> Chuck Magee | Y6: =IF(U6<0,"Zərər",IF(U6<100,"Aşağı Qazanc","Yüksək Qazanc")) -> Aşağı Qazanc
A7: =A6+1 -> 6 | B7: US-2023-167199 | C7: 44932 | D7: 44936 | E7: Standard Class | F7: ME-17320 | G7: Maria Etezadi | H7: Home Office | I7: United States | J7: Henderson | K7: Kentucky | L7: 42420 | M7: South | N7: FUR-CH-10004063 | O7: Furniture | P7: Chairs | Q7: Global Deluxe High-Back Manager's Chair | R7: 2573.82 | S7: 9 | T7: 0 | U7: 746.4078 | W7: =INDEX(People!A:A,MATCH(M7,People!B:B,0)) -> Fred Suzuki | Y7: =IF(U7<0,"Zərər",IF(U7<100,"Aşağı Qazanc","Yüksək Qazanc")) -> Yüksək Qazanc
A8: =A7+1 -> 7 | B8: US-2023-167199 | C8: 44932 | D8: 44936 | E8: Standard Class | F8: ME-17320 | G8: Maria Etezadi | H8: Home Office | I8: United States | J8: Henderson | K8: Kentucky | L8: 42420 | M8: South | N8: OFF-AR-10001662 | O8: Office Supplies | P8: Art | Q8: Rogers Handheld Barrel Pencil Sharpener | R8: 5.48 | S8: 2 | T8: 0 | U8: 1.4796 | W8: =INDEX(People!A:A,MATCH(M8,People!B:B,0)) -> Fred Suzuki | Y8: =IF(U8<0,"Zərər",IF(U8<100,"Aşağı Qazanc","Yüksək Qazanc")) -> Aşağı Qazanc
A9: =A8+1 -> 8 | B9: US-2023-106054 | C9: 44932 | D9: 44933 | E9: First Class | F9: JO-15145 | G9: Jack O'Briant | H9: Corporate | I9: United States | J9: Athens | K9: Georgia | L9: 30605 | M9: South | N9: OFF-AR-10002399 | O9: Office Supplies | P9: Art | Q9: Dixon Prang Watercolor Pencils, 10-Color Set with Brush | R9: 12.78 | S9: 3 | T9: 0 | U9: 5.2398 | W9: =INDEX(People!A:A,MATCH(M9,People!B:B,0)) -> Fred Suzuki | Y9: =IF(U9<0,"Zərər",IF(U9<100,"Aşağı Qazanc","Yüksək Qazanc")) -> Aşağı Qazanc
A10: =A9+1 -> 9 | B10: US-2023-167199 | C10: 44932 | D10: 44936 | E10: Standard Class | F10: ME-17320 | G10: Maria Etezadi | H10: Home Office | I10: United States | J10: Henderson | K10: Kentucky | L10: 42420 | M10: South | N10: OFF-BI-10004632 | O10: Office Supplies | P10: Binders | Q10: Ibico Hi-Tech Manual Binding System | R10: 609.98 | S10: 2 | T10: 0 | U10: 274.491 | W10: =INDEX(People!A:A,MATCH(M10,People!B:B,0)) -> Fred Suzuki | Y10: =IF(U10<0,"Zərər",IF(U10<100,"Aşağı Qazanc","Yüksək Qazanc")) -> Yüksək Qazanc
A11: =A10+1 -> 10 | B11: US-2023-167199 | C11: 44932 | D11: 44936 | E11: Standard Class | F11: ME-17320 | G11: Maria Etezadi | H11: Home Office | I11: United States | J11: Henderson | K11: Kentucky | L11: 42420 | M11: South | N11: OFF-FA-10001883 | O11: Office Supplies | P11: Fasteners | Q11: Alliance Super-Size Bands, Assorted Sizes | R11: 31.12 | S11: 4 | T11: 0 | U11: 0.3112 | W11: =INDEX(People!A:A,MATCH(M11,People!B:B,0)) -> Fred Suzuki | Y11: =IF(U11<0,"Zərər",IF(U11<100,"Aşağı Qazanc","Yüksək Qazanc")) -> Aşağı Qazanc
A12: =A11+1 -> 11 | B12: US-2023-167199 | C12: 44932 | D12: 44936 | E12: Standard Class | F12: ME-17320 | G12: Maria Etezadi | H12: Home Office | I12: United States | J12: Henderson | K12: Kentucky | L12: 42420 | M12: South | N12: OFF-PA-10000955 | O12: Office Supplies | P12: Paper | Q12: Southworth 25% Cotton Granite Paper & Envelopes | R12: 6.54 | S12: 1 | T12: 0 | U12: 3.0084 | W12: =INDEX(People!A:A,MATCH(M12,People!B:B,0)) -> Fred Suzuki | Y12: =IF(U12<0,"Zərər",IF(U12<100,"Aşağı Qazanc","Yüksək Qazanc")) -> Aşağı Qazanc
A13: =A12+1 -> 12 | B13: US-2023-130813 | C13: 44932 | D13: 44934 | E13: Second Class | F13: LS-17230 | G13: Lycoris Saunders | H13: Consumer | I13: United States | J13: Los Angeles | K13: California | L13: 90049 | M13: West | N13: OFF-PA-10002005 | O13: Office Supplies | P13: Paper | Q13: Xerox 225 | R13: 19.44 | S13: 3 | T13: 0 | U13: 9.3312 | W13: =INDEX(People!A:A,MATCH(M13,People!B:B,0)) -> Sadie Pawthorne | Y13: =IF(U13<0,"Zərər",IF(U13<100,"Aşağı Qazanc","Yüksək Qazanc")) -> Aşağı Qazanc
A14: =A13+1 -> 13 | B14: US-2023-167199 | C14: 44932 | D14: 44936 | E14: Standard Class | F14: ME-17320 | G14: Maria Etezadi | H14: Home Office | I14: United States | J14: Henderson | K14: Kentucky | L14: 42420 | M14: South | N14: TEC-PH-10004539 | O14: Technology | P14: Phones | Q14: Wireless Extenders zBoost YX545 SOHO Signal Booster | R14: 755.96 | S14: 4 | T14: 0 | U14: 204.1092 | W14: =INDEX(People!A:A,MATCH(M14,People!B:B,0)) -> Fred Suzuki | Y14: =IF(U14<0,"Zərər",IF(U14<100,"Aşağı Qazanc","Yüksək Qazanc")) -> Yüksək Qazanc
... A62: =A61+1 -> 61 | B62: US-2023-110422 | C62: 44947 | D62: 44949 | E62: Second Class | F62: TB-21400 | G62: Tom Boeckenhauer | H62: Consumer | I62: United States | J62: Miami | K62: Florida | L62: 33180 | M62: South | N62: FUR-FU-10001889 | O62: Furniture | P62: Furnishings | Q62: Ultra Door Pull Handle | R62: 25.248 | S62: 3 | T62: 0.2 | U62: 4.1028 | W62: =INDEX(People!A:A,MATCH(M62,People!B:B,0)) -> Fred Suzuki | Y62: =IF(U62<0,"Zərər",IF(U62<100,"Aşağı Qazanc","Yüksək Qazanc")) -> Aşağı Qazanc
A63: =A62+1 -> 62 | B63: CA-2023-115238 | C63: 44947 | D63: 44950 | E63: Standard Class | F63: JW-15220 | G63: Jane Waco | H63: Corporate | I63: Canada | J63: Toronto | K63: Ontario | L63: M7A | M63: East | N63: FUR-FU-10001025 | O63: Furniture | P63: Furnishings | Q63: Eldon Imàge Series Desk Accessories, Clear | R63: 24.3 | S63: 5 | T63: 0 | U63: 10.45 | W63: =INDEX(People!A:A,MATCH(M63,People!B:B,0)) -> Chuck Magee | Y63: =IF(U63<0,"Zərər",IF(U63<100,"Aşağı Qazanc","Yüksək Qazanc")) -> Aşağı Qazanc
A64: =A63+1 -> 63 | B64: CA-2023-115238 | C64: 44947 | D64: 44950 | E64: Standard Class | F64: JW-15220 | G64: Jane Waco | H64: Corporate | I64: Canada | J64: Toronto | K64: Ontario | L64: M7A | M64: East | N64: FUR-FU-10002445 | O64: Furniture | P64: Furnishings | Q64: DAX Two-Tone Rosewood/Black Document Frame, Desktop, 5 x 7 | R64: 9.48 | S64: 1 | T64: 0 | U64: 3.79 | W64: =INDEX(People!A:A,MATCH(M64,People!B:B,0)) -> Chuck Magee | Y64: =IF(U64<0,"Zərər",IF(U64<100,"Aşağı Qazanc","Yüksək Qazanc")) -> Aşağı Qazanc
A65: =A64+1 -> 64 | B65: CA-2023-115238 | C65: 44947 | D65: 44950 | E65: Standard Class | F65: JW-15220 | G65: Jane Waco | H65: Corporate | I65: Canada | J65: Toronto | K65: Ontario | L65: M7A | M65: East | N65: FUR-FU-10002960 | O65: Furniture | P65: Furnishings | Q65: Eldon 200 Class Desk Accessories, Burgundy | R65: 31.4 | S65: 5 | T65: 0 | U65: 13.19 | W65: =INDEX(People!A:A,MATCH(M65,People!B:B,0)) -> Chuck Magee | Y65: =IF(U65<0,"Zərər",IF(U65<100,"Aşağı Qazanc","Yüksək Qazanc")) -> Aşağı Qazanc
A66: =A65+1 -> 65 | B66: CA-2023-115238 | C66: 44947 | D66: 44950 | E66: Standard Class | F66: JW-15220 | G66: Jane Waco | H66: Corporate | I66: Canada | J66: Toronto | K66: Ontario | L66: M7A | M66: East | N66: OFF-PA-10002689 | O66: Office Supplies | P66: Paper | Q66: Weyerhaeuser First Choice Laser/Copy Paper (20Lb. and 88 Bright) | R66: 6.48 | S66: 1 | T66: 0 | U66: 3.11 | W66: =INDEX(People!A:A,MATCH(M66,People!B:B,0)) -> Chuck Magee | Y66: =IF(U66<0,"Zərər",IF(U66<100,"Aşağı Qazanc","Yüksək Qazanc")) -> Aşağı Qazanc
A67: =A66+1 -> 66 | B67: CA-2023-115238 | C67: 44947 | D67: 44950 | E67: Standard Class | F67: JW-15220 | G67: Jane Waco | H67: Corporate | I67: Canada | J67: Toronto | K67: Ontario | L67: M7A | M67: East | N67: TEC-PH-10001300 | O67: Technology | P67: Phones | Q67: iKross Bluetooth Portable Keyboard + Cell Phone Stand Holder + Brush for Apple iPhone 5S 5C 5, 4S 4 | R67: 209.5 | S67: 10 | T67: 0 | U67: 58.66 | W67: =INDEX(People!A:A,MATCH(M67,People!B:B,0)) -> Chuck Magee | Y67: =IF(U67<0,"Zərər",IF(U67<100,"Aşağı Qazanc","Yüksək Qazanc")) -> Aşağı Qazanc
A68: =A67+1 -> 67 | B68: US-2023-146997 | C68: 44949 | D68: 44953 | E68: Standard Class | F68: SG-20605 | G68: Speros Goranitis | H68: Consumer | I68: United States | J68: Lafayette | K68: Indiana | L68: 47905 | M68: Central | N68: OFF-FA-10003467 | O68: Office Supplies | P68: Fasteners | Q68: Alliance Big Bands Rubber Bands, 12/Pack | R68: 5.94 | S68: 3 | T68: 0 | U68: 0 | W68: =INDEX(People!A:A,MATCH(M68,People!B:B,0)) -> Roxanne Rodriguez | Y68: =IF(U68<0,"Zərər",IF(U68<100,"Aşağı Qazanc","Yüksək Qazanc")) -> Aşağı Qazanc
A69: =A68+1 -> 68 | B69: US-2023-102645 | C69: 44949 | D69: 44954 | E69: Standard Class | F69: IM-15055 | G69: Ionia McGrath | H69: Consumer | I69: United States | J69: Las Vegas | K69: Nevada | L69: 89115 | M69: West | N69: OFF-PA-10001804 | O69: Office Supplies | P69: Paper | Q69: Xerox 195 | R69: 40.08 | S69: 6 | T69: 0 | U69: 19.2384 | W69: =INDEX(People!A:A,MATCH(M69,People!B:B,0)) -> Sadie Pawthorne | Y69: =IF(U69<0,"Zərər",IF(U69<100,"Aşağı Qazanc","Yüksək Qazanc")) -> Aşağı Qazanc
A70: =A69+1 -> 69 | B70: US-2023-167997 | C70: 44952 | D70: 44955 | E70: First Class | F70: CA-11965 | G70: Carol Adams | H70: Corporate | I70: United States | J70: Rapid City | K70: South Dakota | L70: 57701 | M70: Central | N70: FUR-BO-10004409 | O70: Furniture | P70: Bookcases | Q70: Safco Value Mate Series Steel Bookcases, Baked Enamel Finish on Steel, Gray | R70: 141.96 | S70: 2 | T70: 0 | U70: 39.7488 | W70: =INDEX(People!A:A,MATCH(M70,People!B:B,0)) -> Roxanne Rodriguez | Y70: =IF(U70<0,"Zərər",IF(U70<100,"Aşağı Qazanc","Yüksək Qazanc")) -> Aşağı Qazanc
A71: =A70+1 -> 70 | B71: US-2023-155502 | C71: 44952 | D71: 44957 | E71: Standard Class | F71: SD-20485 | G71: Shirley Daniels | H71: Home Office | I71: United States | J71: Alexandria | K71: Virginia | L71: 22304 | M71: South | N71: FUR-FU-10001847 | O71: Furniture | P71: Furnishings | Q71: Eldon Image Series Black Desk Accessories | R71: 12.42 | S71: 3 | T71: 0 | U71: 4.4712 | W71: =INDEX(People!A:A,MATCH(M71,People!B:B,0)) -> Fred Suzuki | Y71: =IF(U71<0,"Zərər",IF(U71<100,"Aşağı Qazanc","Yüksək Qazanc")) -> Aşağı Qazanc
A72: =A71+1 -> 71 | B72: US-2023-155502 | C72: 44952 | D72: 44957 | E72: Standard Class | F72: SD-20485 | G72: Shirley Daniels | H72: Home Office | I72: United States | J72: Alexandria | K72: Virginia | L72: 22304 | M72: South | N72: FUR-FU-10004587 | O72: Furniture | P72: Furnishings | Q72: GE General Use Halogen Bulbs, 100 Watts, 1 Bulb per Pack | R72: 62.82 | S72: 3 | T72: 0 | U72: 30.7818 | W72: =INDEX(People!A:A,MATCH(M72,People!B:B,0)) -> Fred Suzuki | Y72: =IF(U72<0,"Zərər",IF(U72<100,"Aşağı Qazanc","Yüksək Qazanc")) -> Aşağı Qazanc
A73: =A72+1 -> 72 | B73: US-2023-167997 | C73: 44952 | D73: 44955 | E73: First Class | F73: CA-11965 | G73: Carol Adams | H73: Corporate | I73: United States | J73: Rapid City | K73: South Dakota | L73: 57701 | M73: Central | N73: OFF-BI-10001758 | O73: Office Supplies | P73: Binders | Q73: Wilson Jones 14 Line Acrylic Coated Pressboard Data Binders | R73: 10.68 | S73: 2 | T73: 0 | U73: 5.0196 | W73: =INDEX(People!A:A,MATCH(M73,People!B:B,0)) -> Roxanne Rodriguez | Y73: =IF(U73<0,"Zərər",IF(U73<100,"Aşağı Qazanc","Yüksək Qazanc")) -> Aşağı Qazanc
A74: =A73+1 -> 73 | B74: US-2023-155502 | C74: 44952 | D74: 44957 | E74: Standard Class | F74: SD-20485 | G74: Shirley Daniels | H74: Home Office | I74: United States | J74: Alexandria | K74: Virginia | L74: 22304 | M74: South | N74: OFF-PA-10000380 | O74: Office Supplies | P74: Paper | Q74: REDIFORM Incoming/Outgoing Call Register, 11" X 8 1/2", 100 Messages | R74: 16.68 | S74: 2 | T74: 0 | U74: 8.34 | W74: =INDEX(People!A:A,MATCH(M74,People!B:B,0)) -> Fred Suzuki | Y74: =IF(U74<0,"Zərər",IF(U74<100,"Aşağı Qazanc","Yüksək Qazanc")) -> Aşağı Qazanc
A75: =A74+1 -> 74 | B75: US-2023-155502 | C75: 44952 | D75: 44957 | E75: Standard Class | F75: SD-20485 | G75: Shirley Daniels | H75: Home Office | I75: United States | J75: Alexandria | K75: Virginia | L75: 22304 | M75: South | N75: OFF-PA-10003072 | O75: Office Supplies | P75: Paper | Q75: Eureka Recycled Copy Paper 8 1/2" x 11", Ream | R75: 19.44 | S75: 3 | T75: 0 | U75: 9.3312 | W75: =INDEX(People!A:A,MATCH(M75,People!B:B,0)) -> Fred Suzuki | Y75: =IF(U75<0,"Zərər",IF(U75<100,"Aşağı Qazanc","Yüksək Qazanc")) -> Aşağı Qazanc
A76: =A75+1 -> 75 | B76: US-2023-155502 | C76: 44952 | D76: 44957 | E76: Standard Class | F76: SD-20485 | G76: Shirley Daniels | H76: Home Office | I76: United States | J76: Alexandria | K76: Virginia | L76: 22304 | M76: South | N76: OFF-ST-10004337 | O76: Office Supplies | P76: Storage | Q76: SAFCO Commercial Wire Shelving, 72h | R76: 489.92 | S76: 8 | T76: 0 | U76: 0 | W76: =INDEX(People!A:A,MATCH(M76,People!B:B,0)) -> Fred Suzuki | Y76: =IF(U76<0,"Zərər",IF(U76<100,"Aşağı Qazanc","Yüksək Qazanc")) -> Aşağı Qazanc
A77: =A76+1 -> 76 | B77: US-2023-155502 | C77: 44952 | D77: 44957 | E77: Standard Class | F77: SD-20485 | G77: Shirley Daniels | H77: Home Office | I77: United States | J77: Alexandria | K77: Virginia | L77: 22304 | M77: South | N77: TEC-PH-10002103 | O77: Technology | P77: Phones | Q77: Jabra SPEAK 410 | R77: 187.98 | S77: 2 | T77: 0 | U77: 52.6344 | W77: =INDEX(People!A:A,MATCH(M77,People!B:B,0)) -> Fred Suzuki | Y77: =IF(U77<0,"Zərər",IF(U77<100,"Aşağı Qazanc","Yüksək Qazanc")) -> Aşağı Qazanc
A78: =A77+1 -> 77 | B78: US-2023-155502 | C78: 44952 | D78: 44957 | E78: Standard Class | F78: SD-20485 | G78: Shirley Daniels | H78: Home Office | I78: United States | J78: Alexandria | K78: Virginia | L78: 22304 | M78: South | N78: TEC-PH-10004833 | O78: Technology | P78: Phones | Q78: Macally Suction Cup Mount | R78: 155.35 | S78: 13 | T78: 0 | U78: 0 | W78: =INDEX(People!A:A,MATCH(M78,People!B:B,0)) -> Fred Suzuki | Y78: =IF(U78<0,"Zərər",IF(U78<100,"Aşağı Qazanc","Yüksək Qazanc")) -> Aşağı Qazanc
A79: =A78+1 -> 78 | B79: US-2023-117163 | C79: 44953 | D79: 44959 | E79: Standard Class | F79: EJ-13720 | G79: Ed Jacobs | H79: Consumer | I79: United States | J79: San Diego | K79: California | L79: 92037 | M79: West | N79: FUR-TA-10003469 | O79: Furniture | P79: Tables | Q79: Balt Split Level Computer Training Table | R79: 333 | S79: 3 | T79: 0.2 | U79: -16.65 | W79: =INDEX(People!A:A,MATCH(M79,People!B:B,0)) -> Sadie Pawthorne | Y79: =IF(U79<0,"Zərər",IF(U79<100,"Aşağı Qazanc","Yüksək Qazanc")) -> Zərər
... A99: =A98+1 -> 98 | B99: US-2023-169390 | C99: 44964 | D99: 44967 | E99: Second Class | F99: CS-12250 | G99: Chris Selesnick | H99: Corporate | I99: United States | J99: New York City | K99: New York | L99: 10024 | M99: East | N99: OFF-ST-10001558 | O99: Office Supplies | P99: Storage | Q99: Acco Perma 4000 Stacking Storage Drawers | R99: 64.96 | S99: 4 | T99: 0 | U99: 9.744 | W99: =INDEX(People!A:A,MATCH(M99,People!B:B,0)) -> Chuck Magee | Y99: =IF(U99<0,"Zərər",IF(U99<100,"Aşağı Qazanc","Yüksək Qazanc")) -> Aşağı Qazanc
A100: =A99+1 -> 99 | B100: US-2023-107755 | C100: 44964 | D100: 44969 | E100: Standard Class | F100: CK-12760 | G100: Cyma Kinney | H100: Corporate | I100: United States | J100: Linden | K100: New Jersey | L100: 07036 | M100: East | N100: TEC-AC-10000710 | O100: Technology | P100: Accessories | Q100: Maxell DVD-RAM Discs | R100: 115.36 | S100: 7 | T100: 0 | U100: 49.6048 | W100: =INDEX(People!A:A,MATCH(M100,People!B:B,0)) -> Chuck Magee | Y100: =IF(U100<0,"Zərər",IF(U100<100,"Aşağı Qazanc","Yüksək Qazanc")) -> Aşağı Qazanc
A101: =A100+1 -> 100 | B101: US-2023-125759 | C101: 44965 | D101: 44966 | E101: First Class | F101: NM-18445 | G101: Nathan Mautz | H101: Home Office | I101: United States | J101: North Las Vegas | K101: Nevada | L101: 89031 | M101: West | N101: FUR-FU-10002111 | O101: Furniture | P101: Furnishings | Q101: Master Caster Door Stop, Large Brown | R101: 14.56 | S101: 2 | T101: 0 | U101: 5.5328 | W101: =INDEX(People!A:A,MATCH(M101,People!B:B,0)) -> Sadie Pawthorne | Y101: =IF(U101<0,"Zərər",IF(U101<100,"Aşağı Qazanc","Yüksək Qazanc")) -> Aşağı Qazanc
A102: =A101+1 -> 101 | B102: US-2023-168368 | C102: 44968 | D102: 44972 | E102: Second Class | F102: GA-14725 | G102: Guy Armstrong | H102: Consumer | I102: United States | J102: Columbia | K102: Missouri | L102: 65203 | M102: Central | N102: FUR-CH-10001146 | O102: Furniture | P102: Chairs | Q102: Global Value Mid-Back Manager's Chair, Gray | R102: 60.89 | S102: 1 | T102: 0 | U102: 15.2225 | W102: =INDEX(People!A:A,MATCH(M102,People!B:B,0)) -> Roxanne Rodriguez | Y102: =IF(U102<0,"Zərər",IF(U102<100,"Aşağı Qazanc","Yüksək Qazanc")) -> Aşağı Qazanc
A103: =A102+1 -> 102 | B103: US-2023-168368 | C103: 44968 | D103: 44972 | E103: Second Class | F103: GA-14725 | G103: Guy Armstrong | H103: Consumer | I103: United States | J103: Columbia | K103: Missouri | L103: 65203 | M103: Central | N103: FUR-FU-10002298 | O103: Furniture | P103: Furnishings | Q103: Rubbermaid ClusterMat Chairmats, Mat Size- 66" x 60", Lip 20" x 11" -90 Degree Angle | R103: 332.94 | S103: 3 | T103: 0 | U103: 53.2704 | W103: =INDEX(People!A:A,MATCH(M103,People!B:B,0)) -> Roxanne Rodriguez | Y103: =IF(U103<0,"Zərər",IF(U103<100,"Aşağı Qazanc","Yüksək Qazanc")) -> Aşağı Qazanc
A104: =A103+1 -> 103 | B104: US-2023-127614 | C104: 44968 | D104: 44972 | E104: Standard Class | F104: NF-18385 | G104: Natalie Fritzler | H104: Consumer | I104: United States | J104: Chesapeake | K104: Virginia | L104: 23320 | M104: South | N104: FUR-TA-10003715 | O104: Furniture | P104: Tables | Q104: Hon 2111 Invitation Series Corner Table | R104: 1256.22 | S104: 6 | T104: 0 | U104: 75.3732 | W104: =INDEX(People!A:A,MATCH(M104,People!B:B,0)) -> Fred Suzuki | Y104: =IF(U104<0,"Zərər",IF(U104<100,"Aşağı Qazanc","Yüksək Qazanc")) -> Aşağı Qazanc
A105: =A104+1 -> 104 | B105: US-2023-127614 | C105: 44968 | D105: 44972 | E105: Standard Class | F105: NF-18385 | G105: Natalie Fritzler | H105: Consumer | I105: United States | J105: Chesapeake | K105: Virginia | L105: 23320 | M105: South | N105: OFF-BI-10003291 | O105: Office Supplies | P105: Binders | Q105: Wilson Jones Leather-Like Binders with DublLock Round Rings | R105: 17.46 | S105: 2 | T105: 0 | U105: 8.2062 | W105: =INDEX(People!A:A,MATCH(M105,People!B:B,0)) -> Fred Suzuki | Y105: =IF(U105<0,"Zərər",IF(U105<100,"Aşağı Qazanc","Yüksək Qazanc")) -> Aşağı Qazanc
A106: =A105+1 -> 105 | B106: US-2023-168368 | C106: 44968 | D106: 44972 | E106: Second Class | F106: GA-14725 | G106: Guy Armstrong | H106: Consumer | I106: United States | J106: Columbia | K106: Missouri | L106: 65203 | M106: Central | N106: OFF-BI-10004654 | O106: Office Supplies | P106: Binders | Q106: VariCap6 Expandable Binder | R106: 51.9 | S106: 3 | T106: 0 | U106: 24.393 | W106: =INDEX(People!A:A,MATCH(M106,People!B:B,0)) -> Roxanne Rodriguez | Y106: =IF(U106<0,"Zərər",IF(U106<100,"Aşağı Qazanc","Yüksək Qazanc")) -> Aşağı Qazanc
A107: =A106+1 -> 106 | B107: US-2023-168368 | C107: 44968 | D107: 44972 | E107: Second Class | F107: GA-14725 | G107: Guy Armstrong | H107: Consumer | I107: United States | J107: Columbia | K107: Missouri | L107: 65203 | M107: Central | N107: OFF-BI-10004728 | O107: Office Supplies | P107: Binders | Q107: Wilson Jones Turn Tabs Binder Tool for Ring Binders | R107: 9.64 | S107: 2 | T107: 0 | U107: 4.4344 | W107: =INDEX(People!A:A,MATCH(M107,People!B:B,0)) -> Roxanne Rodriguez | Y107: =IF(U107<0,"Zərər",IF(U107<100,"Aşağı Qazanc","Yüksək Qazanc")) -> Aşağı Qazanc
A108: =A107+1 -> 107 | B108: US-2023-168368 | C108: 44968 | D108: 44972 | E108: Second Class | F108: GA-14725 | G108: Guy Armstrong | H108: Consumer | I108: United States | J108: Columbia | K108: Missouri | L108: 65203 | M108: Central | N108: OFF-LA-10004853 | O108: Office Supplies | P108: Labels | Q108: Avery 483 | R108: 14.94 | S108: 3 | T108: 0 | U108: 6.8724 | W108: =INDEX(People!A:A,MATCH(M108,People!B:B,0)) -> Roxanne Rodriguez | Y108: =IF(U108<0,"Zərər",IF(U108<100,"Aşağı Qazanc","Yüksək Qazanc")) -> Aşağı Qazanc
A109: =A108+1 -> 108 | B109: US-2023-168368 | C109: 44968 | D109: 44972 | E109: Second Class | F109: GA-14725 | G109: Guy Armstrong | H109: Consumer | I109: United States | J109: Columbia | K109: Missouri | L109: 65203 | M109: Central | N109: OFF-ST-10002583 | O109: Office Supplies | P109: Storage | Q109: Fellowes Neat Ideas Storage Cubes | R109: 64.96 | S109: 2 | T109: 0 | U109: 2.5984 | W109: =INDEX(People!A:A,MATCH(M109,People!B:B,0)) -> Roxanne Rodriguez | Y109: =IF(U109<0,"Zərər",IF(U109<100,"Aşağı Qazanc","Yüksək Qazanc")) -> Aşağı Qazanc
A110: =A109+1 -> 109 | B110: US-2023-127614 | C110: 44968 | D110: 44972 | E110: Standard Class | F110: NF-18385 | G110: Natalie Fritzler | H110: Consumer | I110: United States | J110: Chesapeake | K110: Virginia | L110: 23320 | M110: South | N110: TEC-AC-10001432 | O110: Technology | P110: Accessories | Q110: Enermax Aurora Lite Keyboard | R110: 234.45 | S110: 3 | T110: 0 | U110: 103.158 | W110: =INDEX(People!A:A,MATCH(M110,People!B:B,0)) -> Fred Suzuki | Y110: =IF(U110<0,"Zərər",IF(U110<100,"Aşağı Qazanc","Yüksək Qazanc")) -> Yüksək Qazanc
A111: =A110+1 -> 110 | B111: US-2023-110674 | C111: 44969 | D111: 44975 | E111: Standard Class | F111: SC-20095 | G111: Sanjit Chand | H111: Consumer | I111: United States | J111: Concord | K111: California | L111: 94521 | M111: West | N111: FUR-CH-10000225 | O111: Furniture | P111: Chairs | Q111: Global Geo Office Task Chair, Gray | R111: 129.568 | S111: 2 | T111: 0.2 | U111: -24.294 | W111: =INDEX(People!A:A,MATCH(M111,People!B:B,0)) -> Sadie Pawthorne | Y111: =IF(U111<0,"Zərər",IF(U111<100,"Aşağı Qazanc","Yüksək Qazanc")) -> Zərər
A112: =A111+1 -> 111 | B112: US-2023-121762 | C112: 44971 | D112: 44975 | E112: Standard Class | F112: ML-17395 | G112: Marina Lichtenstein | H112: Corporate | I112: United States | J112: Seattle | K112: Washington | L112: 98103 | M112: West | N112: OFF-AP-10001293 | O112: Office Supplies | P112: Appliances | Q112: Belkin 8 Outlet Surge Protector | R112: 81.96 | S112: 2 | T112: 0 | U112: 22.9488 | W112: =INDEX(People!A:A,MATCH(M112,People!B:B,0)) -> Sadie Pawthorne | Y112: =IF(U112<0,"Zərər",IF(U112<100,"Aşağı Qazanc","Yüksək Qazanc")) -> Aşağı Qazanc
... A180: =A179+1 -> 179 | B180: US-2023-114790 | C180: 44996 | D180: 44998 | E180: Second Class | F180: FM-14215 | G180: Filia McAdams | H180: Corporate | I180: United States | J180: Richmond | K180: Kentucky | L180: 40475 | M180: South | N180: TEC-PH-10000984 | O180: Technology | P180: Phones | Q180: Panasonic KX-TG9471B | R180: 587.97 | S180: 3 | T180: 0 | U180: 164.6316 | W180: =INDEX(People!A:A,MATCH(M180,People!B:B,0)) -> Fred Suzuki | Y180: =IF(U180<0,"Zərər",IF(U180<100,"Aşağı Qazanc","Yüksək Qazanc")) -> Yüksək Qazanc
A181: =A180+1 -> 180 | B181: CA-2023-139675 | C181: 44998 | D181: 45003 | E181: Second Class | F181: NF-18595 | G181: Nicole Fjeld | H181: Home Office | I181: Canada | J181: Calgary | K181: Alberta | L181: T2C | M181: West | N181: FUR-CH-10004063 | O181: Furniture | P181: Chairs | Q181: Global Deluxe High-Back Manager's Chair | R181: 915.14 | S181: 4 | T181: 0.2 | U181: 102.95 | W181: =INDEX(People!A:A,MATCH(M181,People!B:B,0)) -> Sadie Pawthorne | Y181: =IF(U181<0,"Zərər",IF(U181<100,"Aşağı Qazanc","Yüksək Qazanc")) -> Yüksək Qazanc
A182: =A181+1 -> 181 | B182: CA-2023-139675 | C182: 44998 | D182: 45003 | E182: Second Class | F182: NF-18595 | G182: Nicole Fjeld | H182: Home Office | I182: Canada | J182: Calgary | K182: Alberta | L182: T2C | M182: West | N182: FUR-FU-10001979 | O182: Furniture | P182: Furnishings | Q182: Dana Halogen Swing-Arm Architect Lamp | R182: 327.76 | S182: 8 | T182: 0 | U182: 91.77 | W182: =INDEX(People!A:A,MATCH(M182,People!B:B,0)) -> Sadie Pawthorne | Y182: =IF(U182<0,"Zərər",IF(U182<100,"Aşağı Qazanc","Yüksək Qazanc")) -> Aşağı Qazanc
A183: =A182+1 -> 182 | B183: US-2023-125521 | C183: 44999 | D183: 45004 | E183: Standard Class | F183: CK-12325 | G183: Christine Kargatis | H183: Home Office | I183: United States | J183: Chesapeake | K183: Virginia | L183: 23320 | M183: South | N183: FUR-CH-10003379 | O183: Furniture | P183: Chairs | Q183: Global Commerce Series High-Back Swivel/Tilt Chairs | R183: 1139.92 | S183: 4 | T183: 0 | U183: 284.98 | W183: =INDEX(People!A:A,MATCH(M183,People!B:B,0)) -> Fred Suzuki | Y183: =IF(U183<0,"Zərər",IF(U183<100,"Aşağı Qazanc","Yüksək Qazanc")) -> Yüksək Qazanc
A184: =A183+1 -> 183 | B184: US-2023-157623 | C184: 44999 | D184: 45003 | E184: Standard Class | F184: DK-13225 | G184: Dean Katz | H184: Corporate | I184: United States | J184: Huntington Beach | K184: California | L184: 92646 | M184: West | N184: OFF-AR-10003723 | O184: Office Supplies | P184: Art | Q184: Avery Hi-Liter Fluorescent Desk Style Markers | R184: 3.38 | S184: 1 | T184: 0 | U184: 1.2506 | W184: =INDEX(People!A:A,MATCH(M184,People!B:B,0)) -> Sadie Pawthorne | Y184: =IF(U184<0,"Zərər",IF(U184<100,"Aşağı Qazanc","Yüksək Qazanc")) -> Aşağı Qazanc
A185: =A184+1 -> 184 | B185: US-2023-114510 | C185: 44999 | D185: 45004 | E185: Standard Class | F185: JF-15295 | G185: Jason Fortune- | H185: Consumer | I185: United States | J185: Logan | K185: Utah | L185: 84321 | M185: West | N185: OFF-BI-10001617 | O185: Office Supplies | P185: Binders | Q185: GBC Wire Binding Combs | R185: 33.088 | S185: 4 | T185: 0.2 | U185: 11.1672 | W185: =INDEX(People!A:A,MATCH(M185,People!B:B,0)) -> Sadie Pawthorne | Y185: =IF(U185<0,"Zərər",IF(U185<100,"Aşağı Qazanc","Yüksək Qazanc")) -> Aşağı Qazanc
A186: =A185+1 -> 185 | B186: US-2023-114510 | C186: 44999 | D186: 45004 | E186: Standard Class | F186: JF-15295 | G186: Jason Fortune- | H186: Consumer | I186: United States | J186: Logan | K186: Utah | L186: 84321 | M186: West | N186: OFF-BI-10003007 | O186: Office Supplies | P186: Binders | Q186: Premium Transparent Presentation Covers, No Pattern/Clear, 8 1/2" x 11" | R186: 62.048 | S186: 2 | T186: 0.2 | U186: 20.1656 | W186: =INDEX(People!A:A,MATCH(M186,People!B:B,0)) -> Sadie Pawthorne | Y186: =IF(U186<0,"Zərər",IF(U186<100,"Aşağı Qazanc","Yüksək Qazanc")) -> Aşağı Qazanc
A187: =A186+1 -> 186 | B187: US-2023-100293 | C187: 44999 | D187: 45003 | E187: Standard Class | F187: NF-18475 | G187: Neil Französisch | H187: Home Office | I187: United States | J187: Jacksonville | K187: Florida | L187: 32216 | M187: South | N187: OFF-PA-10000176 | O187: Office Supplies | P187: Paper | Q187: Xerox 1887 | R187: 91.056 | S187: 6 | T187: 0.2 | U187: 31.8696 | W187: =INDEX(People!A:A,MATCH(M187,People!B:B,0)) -> Fred Suzuki | Y187: =IF(U187<0,"Zərər",IF(U187<100,"Aşağı Qazanc","Yüksək Qazanc")) -> Aşağı Qazanc
A188: =A187+1 -> 187 | B188: US-2023-157623 | C188: 44999 | D188: 45003 | E188: Standard Class | F188: DK-13225 | G188: Dean Katz | H188: Corporate | I188: United States | J188: Huntington Beach | K188: California | L188: 92646 | M188: West | N188: OFF-PA-10001204 | O188: Office Supplies | P188: Paper | Q188: Xerox 1972 | R188: 10.56 | S188: 2 | T188: 0 | U188: 4.752 | W188: =INDEX(People!A:A,MATCH(M188,People!B:B,0)) -> Sadie Pawthorne | Y188: =IF(U188<0,"Zərər",IF(U188<100,"Aşağı Qazanc","Yüksək Qazanc")) -> Aşağı Qazanc
A189: =A188+1 -> 188 | B189: US-2023-152618 | C189: 44999 | D189: 45002 | E189: First Class | F189: RB-19465 | G189: Rick Bensley | H189: Home Office | I189: United States | J189: Chicago | K189: Illinois | L189: 60653 | M189: Central | N189: OFF-PA-10001215 | O189: Office Supplies | P189: Paper | Q189: Xerox 1963 | R189: 8.448 | S189: 2 | T189: 0.2 | U189: 2.64 | W189: =INDEX(People!A:A,MATCH(M189,People!B:B,0)) -> Roxanne Rodriguez | Y189: =IF(U189<0,"Zərər",IF(U189<100,"Aşağı Qazanc","Yüksək Qazanc")) -> Aşağı Qazanc
A190: =A189+1 -> 189 | B190: US-2023-114510 | C190: 44999 | D190: 45004 | E190: Standard Class | F190: JF-15295 | G190: Jason Fortune- | H190: Consumer | I190: United States | J190: Logan | K190: Utah | L190: 84321 | M190: West | N190: OFF-ST-10000736 | O190: Office Supplies | P190: Storage | Q190: Carina Double Wide Media Storage Towers in Natural & Black | R190: 80.98 | S190: 1 | T190: 0 | U190: 3.2392 | W190: =INDEX(People!A:A,MATCH(M190,People!B:B,0)) -> Sadie Pawthorne | Y190: =IF(U190<0,"Zərər",IF(U190<100,"Aşağı Qazanc","Yüksək Qazanc")) -> Aşağı Qazanc
A191: =A190+1 -> 190 | B191: US-2023-114510 | C191: 44999 | D191: 45004 | E191: Standard Class | F191: JF-15295 | G191: Jason Fortune- | H191: Consumer | I191: United States | J191: Logan | K191: Utah | L191: 84321 | M191: West | N191: OFF-ST-10003221 | O191: Office Supplies | P191: Storage | Q191: Staple magnet | R191: 21.36 | S191: 2 | T191: 0 | U191: 5.7672 | W191: =INDEX(People!A:A,MATCH(M191,People!B:B,0)) -> Sadie Pawthorne | Y191: =IF(U191<0,"Zərər",IF(U191<100,"Aşağı Qazanc","Yüksək Qazanc")) -> Aşağı Qazanc
A192: =A191+1 -> 191 | B192: US-2023-114510 | C192: 44999 | D192: 45004 | E192: Standard Class | F192: JF-15295 | G192: Jason Fortune- | H192: Consumer | I192: United States | J192: Logan | K192: Utah | L192: 84321 | M192: West | N192: TEC-AC-10004877 | O192: Technology | P192: Accessories | Q192: Imation 30456 USB Flash Drive 8GB | R192: 82.8 | S192: 12 | T192: 0 | U192: 6.624 | W192: =INDEX(People!A:A,MATCH(M192,People!B:B,0)) -> Sadie Pawthorne | Y192: =IF(U192<0,"Zərər",IF(U192<100,"Aşağı Qazanc","Yüksək Qazanc")) -> Aşağı Qazanc
A193: =A192+1 -> 192 | B193: US-2023-152618 | C193: 44999 | D193: 45002 | E193: First Class | F193: RB-19465 | G193: Rick Bensley | H193: Home Office | I193: United States | J193: Chicago | K193: Illinois | L193: 60653 | M193: Central | N193: TEC-MA-10003626 | O193: Technology | P193: Machines | Q193: Hewlett-Packard Deskjet 6540 Color Inkjet Printer | R193: 574.91 | S193: 2 | T193: 0.3 | U193: 156.047 | W193: =INDEX(People!A:A,MATCH(M193,People!B:B,0)) -> Roxanne Rodriguez | Y193: =IF(U193<0,"Zərər",IF(U193<100,"Aşağı Qazanc","Yüksək Qazanc")) -> Yüksək Qazanc
A194: =A193+1 -> 193 | B194: US-2023-149958 | C194: 45000 | D194: 45004 | E194: Standard Class | F194: AS-10240 | G194: Alan Shonely | H194: Consumer | I194: United States | J194: Tampa | K194: Florida | L194: 33614 | M194: South | N194: FUR-FU-10001756 | O194: Furniture | P194: Furnishings | Q194: Eldon Expressions Desk Accessory, Wood Photo Frame, Mahogany | R194: 45.696 | S194: 3 | T194: 0.2 | U194: 5.1408 | W194: =INDEX(People!A:A,MATCH(M194,People!B:B,0)) -> Fred Suzuki | Y194: =IF(U194<0,"Zərər",IF(U194<100,"Aşağı Qazanc","Yüksək Qazanc")) -> Aşağı Qazanc
... A291: =A290+1 -> 290 | B291: US-2023-157021 | C291: 45017 | D291: 45022 | E291: Second Class | F291: KM-16720 | G291: Kunst Miller | H291: Consumer | I291: United States | J291: Vallejo | K291: California | L291: 94591 | M291: West | N291: OFF-BI-10000042 | O291: Office Supplies | P291: Binders | Q291: Pressboard Data Binder, Crimson, 12" X 8 1/2" | R291: 17.088 | S291: 4 | T291: 0.2 | U291: 5.5536 | W291: =INDEX(People!A:A,MATCH(M291,People!B:B,0)) -> Sadie Pawthorne | Y291: =IF(U291<0,"Zərər",IF(U291<100,"Aşağı Qazanc","Yüksək Qazanc")) -> Aşağı Qazanc
A292: =A291+1 -> 291 | B292: US-2023-138359 | C292: 45017 | D292: 45022 | E292: Standard Class | F292: KH-16330 | G292: Katharine Harms | H292: Corporate | I292: United States | J292: Revere | K292: Massachusetts | L292: 02151 | M292: East | N292: OFF-BI-10000145 | O292: Office Supplies | P292: Binders | Q292: Zipper Ring Binder Pockets | R292: 6.24 | S292: 2 | T292: 0 | U292: 3.0576 | W292: =INDEX(People!A:A,MATCH(M292,People!B:B,0)) -> Chuck Magee | Y292: =IF(U292<0,"Zərər",IF(U292<100,"Aşağı Qazanc","Yüksək Qazanc")) -> Aşağı Qazanc
A293: =A292+1 -> 292 | B293: US-2023-157021 | C293: 45017 | D293: 45022 | E293: Second Class | F293: KM-16720 | G293: Kunst Miller | H293: Consumer | I293: United States | J293: Vallejo | K293: California | L293: 94591 | M293: West | N293: OFF-LA-10002312 | O293: Office Supplies | P293: Labels | Q293: Avery 490 | R293: 29.6 | S293: 2 | T293: 0 | U293: 14.8 | W293: =INDEX(People!A:A,MATCH(M293,People!B:B,0)) -> Sadie Pawthorne | Y293: =IF(U293<0,"Zərər",IF(U293<100,"Aşağı Qazanc","Yüksək Qazanc")) -> Aşağı Qazanc
A294: =A293+1 -> 293 | B294: US-2023-138359 | C294: 45017 | D294: 45022 | E294: Standard Class | F294: KH-16330 | G294: Katharine Harms | H294: Corporate | I294: United States | J294: Revere | K294: Massachusetts | L294: 02151 | M294: East | N294: OFF-ST-10000636 | O294: Office Supplies | P294: Storage | Q294: Rogers Profile Extra Capacity Storage Tub | R294: 66.96 | S294: 4 | T294: 0 | U294: 2.6784 | W294: =INDEX(People!A:A,MATCH(M294,People!B:B,0)) -> Chuck Magee | Y294: =IF(U294<0,"Zərər",IF(U294<100,"Aşağı Qazanc","Yüksək Qazanc")) -> Aşağı Qazanc
A295: =A294+1 -> 294 | B295: US-2023-160276 | C295: 45018 | D295: 45024 | E295: Standard Class | F295: AH-10690 | G295: Anna Häberlin | H295: Corporate | I295: United States | J295: Virginia Beach | K295: Virginia | L295: 23464 | M295: South | N295: FUR-FU-10003192 | O295: Furniture | P295: Furnishings | Q295: Luxo Adjustable Task Clamp Lamp | R295: 177.68 | S295: 2 | T295: 0 | U295: 46.1968 | W295: =INDEX(People!A:A,MATCH(M295,People!B:B,0)) -> Fred Suzuki | Y295: =IF(U295<0,"Zərər",IF(U295<100,"Aşağı Qazanc","Yüksək Qazanc")) -> Aşağı Qazanc
A296: =A295+1 -> 295 | B296: US-2023-164315 | C296: 45018 | D296: 45024 | E296: Standard Class | F296: RD-19585 | G296: Rob Dowd | H296: Consumer | I296: United States | J296: Athens | K296: Georgia | L296: 30605 | M296: South | N296: OFF-AP-10003842 | O296: Office Supplies | P296: Appliances | Q296: Euro-Pro Shark Turbo Vacuum | R296: 154.9 | S296: 5 | T296: 0 | U296: 40.274 | W296: =INDEX(People!A:A,MATCH(M296,People!B:B,0)) -> Fred Suzuki | Y296: =IF(U296<0,"Zərər",IF(U296<100,"Aşağı Qazanc","Yüksək Qazanc")) -> Aşağı Qazanc
A297: =A296+1 -> 296 | B297: US-2023-157847 | C297: 45018 | D297: 45022 | E297: Second Class | F297: SC-20020 | G297: Sam Craven | H297: Consumer | I297: United States | J297: Houston | K297: Texas | L297: 77095 | M297: Central | N297: OFF-PA-10001593 | O297: Office Supplies | P297: Paper | Q297: Xerox 1947 | R297: 33.488 | S297: 7 | T297: 0.2 | U297: 10.465 | W297: =INDEX(People!A:A,MATCH(M297,People!B:B,0)) -> Roxanne Rodriguez | Y297: =IF(U297<0,"Zərər",IF(U297<100,"Aşağı Qazanc","Yüksək Qazanc")) -> Aşağı Qazanc
A298: =A297+1 -> 297 | B298: US-2023-157847 | C298: 45018 | D298: 45022 | E298: Second Class | F298: SC-20020 | G298: Sam Craven | H298: Consumer | I298: United States | J298: Houston | K298: Texas | L298: 77095 | M298: Central | N298: OFF-PA-10002986 | O298: Office Supplies | P298: Paper | Q298: Xerox 1898 | R298: 26.72 | S298: 5 | T298: 0.2 | U298: 9.352 | W298: =INDEX(People!A:A,MATCH(M298,People!B:B,0)) -> Roxanne Rodriguez | Y298: =IF(U298<0,"Zərər",IF(U298<100,"Aşağı Qazanc","Yüksək Qazanc")) -> Aşağı Qazanc
A299: =A298+1 -> 298 | B299: US-2023-164315 | C299: 45018 | D299: 45024 | E299: Standard Class | F299: RD-19585 | G299: Rob Dowd | H299: Consumer | I299: United States | J299: Athens | K299: Georgia | L299: 30605 | M299: South | N299: OFF-PA-10004248 | O299: Office Supplies | P299: Paper | Q299: Xerox 1990 | R299: 15.84 | S299: 3 | T299: 0 | U299: 7.128 | W299: =INDEX(People!A:A,MATCH(M299,People!B:B,0)) -> Fred Suzuki | Y299: =IF(U299<0,"Zərər",IF(U299<100,"Aşağı Qazanc","Yüksək Qazanc")) -> Aşağı Qazanc
A300: =A299+1 -> 299 | B300: US-2023-164315 | C300: 45018 | D300: 45024 | E300: Standard Class | F300: RD-19585 | G300: Rob Dowd | H300: Consumer | I300: United States | J300: Athens | K300: Georgia | L300: 30605 | M300: South | N300: TEC-PH-10001128 | O300: Technology | P300: Phones | Q300: Motorola Droid Maxx | R300: 1049.93 | S300: 7 | T300: 0 | U300: 293.9804 | W300: =INDEX(People!A:A,MATCH(M300,People!B:B,0)) -> Fred Suzuki | Y300: =IF(U300<0,"Zərər",IF(U300<100,"Aşağı Qazanc","Yüksək Qazanc")) -> Yüksək Qazanc
A301: =A300+1 -> 300 | B301: US-2023-112291 | C301: 45019 | D301: 45024 | E301: Standard Class | F301: KE-16420 | G301: Katrina Edelman | H301: Corporate | I301: United States | J301: Los Angeles | K301: California | L301: 90008 | M301: West | N301: OFF-EN-10001415 | O301: Office Supplies | P301: Envelopes | Q301: Staple envelope | R301: 11.16 | S301: 2 | T301: 0 | U301: 5.58 | W301: =INDEX(People!A:A,MATCH(M301,People!B:B,0)) -> Sadie Pawthorne | Y301: =IF(U301<0,"Zərər",IF(U301<100,"Aşağı Qazanc","Yüksək Qazanc")) -> Aşağı Qazanc
A302: =A301+1 -> 301 | B302: US-2023-112291 | C302: 45019 | D302: 45024 | E302: Standard Class | F302: KE-16420 | G302: Katrina Edelman | H302: Corporate | I302: United States | J302: Los Angeles | K302: California | L302: 90008 | M302: West | N302: TEC-AC-10000736 | O302: Technology | P302: Accessories | Q302: Logitech G600 MMO Gaming Mouse | R302: 159.98 | S302: 2 | T302: 0 | U302: 57.5928 | W302: =INDEX(People!A:A,MATCH(M302,People!B:B,0)) -> Sadie Pawthorne | Y302: =IF(U302<0,"Zərər",IF(U302<100,"Aşağı Qazanc","Yüksək Qazanc")) -> Aşağı Qazanc
A303: =A302+1 -> 302 | B303: US-2023-112291 | C303: 45019 | D303: 45024 | E303: Standard Class | F303: KE-16420 | G303: Katrina Edelman | H303: Corporate | I303: United States | J303: Los Angeles | K303: California | L303: 90008 | M303: West | N303: TEC-AC-10001284 | O303: Technology | P303: Accessories | Q303: Enermax Briskie RF Wireless Keyboard and Mouse Combo | R303: 62.31 | S303: 3 | T303: 0 | U303: 22.4316 | W303: =INDEX(People!A:A,MATCH(M303,People!B:B,0)) -> Sadie Pawthorne | Y303: =IF(U303<0,"Zərər",IF(U303<100,"Aşağı Qazanc","Yüksək Qazanc")) -> Aşağı Qazanc
A304: =A303+1 -> 303 | B304: US-2023-133228 | C304: 45020 | D304: 45025 | E304: Standard Class | F304: MS-17710 | G304: Maurice Satty | H304: Consumer | I304: United States | J304: Detroit | K304: Michigan | L304: 48205 | M304: Central | N304: FUR-FU-10004020 | O304: Furniture | P304: Furnishings | Q304: Advantus Panel Wall Acrylic Frame | R304: 5.47 | S304: 1 | T304: 0 | U304: 2.3521 | W304: =INDEX(People!A:A,MATCH(M304,People!B:B,0)) -> Roxanne Rodriguez | Y304: =IF(U304<0,"Zərər",IF(U304<100,"Aşağı Qazanc","Yüksək Qazanc")) -> Aşağı Qazanc
A305: =A304+1 -> 304 | B305: US-2023-133228 | C305: 45020 | D305: 45025 | E305: Standard Class | F305: MS-17710 | G305: Maurice Satty | H305: Consumer | I305: United States | J305: Detroit | K305: Michigan | L305: 48205 | M305: Central | N305: OFF-AR-10001955 | O305: Office Supplies | P305: Art | Q305: Newell 319 | R305: 79.36 | S305: 4 | T305: 0 | U305: 23.808 | W305: =INDEX(People!A:A,MATCH(M305,People!B:B,0)) -> Roxanne Rodriguez | Y305: =IF(U305<0,"Zərər",IF(U305<100,"Aşağı Qazanc","Yüksək Qazanc")) -> Aşağı Qazanc
A306: =A305+1 -> 305 | B306: US-2023-128685 | C306: 45020 | D306: 45021 | E306: First Class | F306: MZ-17515 | G306: Mary Zewe | H306: Corporate | I306: United States | J306: Los Angeles | K306: California | L306: 90008 | M306: West | N306: OFF-BI-10004140 | O306: Office Supplies | P306: Binders | Q306: Avery Non-Stick Binders | R306: 7.184 | S306: 2 | T306: 0.2 | U306: 2.245 | W306: =INDEX(People!A:A,MATCH(M306,People!B:B,0)) -> Sadie Pawthorne | Y306: =IF(U306<0,"Zərər",IF(U306<100,"Aşağı Qazanc","Yüksək Qazanc")) -> Aşağı Qazanc
... A430: =A429+1 -> 429 | B430: US-2023-130274 | C430: 45049 | D430: 45051 | E430: First Class | F430: JS-15940 | G430: Joni Sundaresam | H430: Home Office | I430: United States | J430: Appleton | K430: Wisconsin | L430: 54915 | M430: Central | N430: OFF-LA-10002195 | O430: Office Supplies | P430: Labels | Q430: Avery 481 | R430: 21.56 | S430: 7 | T430: 0 | U430: 10.3488 | W430: =INDEX(People!A:A,MATCH(M430,People!B:B,0)) -> Roxanne Rodriguez | Y430: =IF(U430<0,"Zərər",IF(U430<100,"Aşağı Qazanc","Yüksək Qazanc")) -> Aşağı Qazanc
A431: =A430+1 -> 430 | B431: US-2023-155271 | C431: 45050 | D431: 45050 | E431: Same Day | F431: AA-10480 | G431: Andrew Allen | H431: Consumer | I431: United States | J431: Middletown | K431: Connecticut | L431: 06457 | M431: East | N431: FUR-FU-10001473 | O431: Furniture | P431: Furnishings | Q431: DAX Wood Document Frame | R431: 27.46 | S431: 2 | T431: 0 | U431: 9.8856 | W431: =INDEX(People!A:A,MATCH(M431,People!B:B,0)) -> Chuck Magee | Y431: =IF(U431<0,"Zərər",IF(U431<100,"Aşağı Qazanc","Yüksək Qazanc")) -> Aşağı Qazanc
A432: =A431+1 -> 431 | B432: US-2023-148194 | C432: 45050 | D432: 45053 | E432: First Class | F432: BS-11365 | G432: Bill Shonely | H432: Corporate | I432: United States | J432: Seattle | K432: Washington | L432: 98105 | M432: West | N432: FUR-FU-10001852 | O432: Furniture | P432: Furnishings | Q432: Eldon Regeneration Recycled Desk Accessories, Smoke | R432: 12.18 | S432: 7 | T432: 0 | U432: 3.8976 | W432: =INDEX(People!A:A,MATCH(M432,People!B:B,0)) -> Sadie Pawthorne | Y432: =IF(U432<0,"Zərər",IF(U432<100,"Aşağı Qazanc","Yüksək Qazanc")) -> Aşağı Qazanc
A433: =A432+1 -> 432 | B433: US-2023-148194 | C433: 45050 | D433: 45053 | E433: First Class | F433: BS-11365 | G433: Bill Shonely | H433: Corporate | I433: United States | J433: Seattle | K433: Washington | L433: 98105 | M433: West | N433: OFF-AP-10000696 | O433: Office Supplies | P433: Appliances | Q433: Holmes Odor Grabber | R433: 57.68 | S433: 4 | T433: 0 | U433: 19.0344 | W433: =INDEX(People!A:A,MATCH(M433,People!B:B,0)) -> Sadie Pawthorne | Y433: =IF(U433<0,"Zərər",IF(U433<100,"Aşağı Qazanc","Yüksək Qazanc")) -> Aşağı Qazanc
A434: =A433+1 -> 433 | B434: US-2023-111899 | C434: 45050 | D434: 45051 | E434: First Class | F434: NC-18340 | G434: Nat Carroll | H434: Consumer | I434: United States | J434: Houston | K434: Texas | L434: 77036 | M434: Central | N434: OFF-AR-10001725 | O434: Office Supplies | P434: Art | Q434: Boston Home & Office Model 2000 Electric Pencil Sharpeners | R434: 37.84 | S434: 2 | T434: 0.2 | U434: 2.838 | W434: =INDEX(People!A:A,MATCH(M434,People!B:B,0)) -> Roxanne Rodriguez | Y434: =IF(U434<0,"Zərər",IF(U434<100,"Aşağı Qazanc","Yüksək Qazanc")) -> Aşağı Qazanc
A435: =A434+1 -> 434 | B435: US-2023-117709 | C435: 45050 | D435: 45054 | E435: Standard Class | F435: PM-18940 | G435: Paul MacIntyre | H435: Consumer | I435: United States | J435: Jackson | K435: Michigan | L435: 49201 | M435: Central | N435: OFF-BI-10001294 | O435: Office Supplies | P435: Binders | Q435: Fellowes Binding Cases | R435: 46.8 | S435: 4 | T435: 0 | U435: 21.06 | W435: =INDEX(People!A:A,MATCH(M435,People!B:B,0)) -> Roxanne Rodriguez | Y435: =IF(U435<0,"Zərər",IF(U435<100,"Aşağı Qazanc","Yüksək Qazanc")) -> Aşağı Qazanc
A436: =A435+1 -> 435 | B436: US-2023-111899 | C436: 45050 | D436: 45051 | E436: First Class | F436: NC-18340 | G436: Nat Carroll | H436: Consumer | I436: United States | J436: Houston | K436: Texas | L436: 77036 | M436: Central | N436: OFF-FA-10000840 | O436: Office Supplies | P436: Fasteners | Q436: OIC Thumb-Tacks | R436: 5.472 | S436: 6 | T436: 0.2 | U436: 1.8468 | W436: =INDEX(People!A:A,MATCH(M436,People!B:B,0)) -> Roxanne Rodriguez | Y436: =IF(U436<0,"Zərər",IF(U436<100,"Aşağı Qazanc","Yüksək Qazanc")) -> Aşağı Qazanc
A437: =A436+1 -> 436 | B437: US-2023-110219 | C437: 45051 | D437: 45054 | E437: First Class | F437: EB-13870 | G437: Emily Burns | H437: Consumer | I437: United States | J437: San Antonio | K437: Texas | L437: 78207 | M437: Central | N437: FUR-CH-10001146 | O437: Furniture | P437: Chairs | Q437: Global Value Mid-Back Manager's Chair, Gray | R437: 127.869 | S437: 3 | T437: 0.3 | U437: -9.1335 | W437: =INDEX(People!A:A,MATCH(M437,People!B:B,0)) -> Roxanne Rodriguez | Y437: =IF(U437<0,"Zərər",IF(U437<100,"Aşağı Qazanc","Yüksək Qazanc")) -> Zərər
A438: =A437+1 -> 437 | B438: US-2023-166457 | C438: 45051 | D438: 45055 | E438: Second Class | F438: PF-19120 | G438: Peter Fuller | H438: Consumer | I438: United States | J438: Richmond | K438: Kentucky | L438: 40475 | M438: South | N438: OFF-AR-10003651 | O438: Office Supplies | P438: Art | Q438: Newell 350 | R438: 6.56 | S438: 2 | T438: 0 | U438: 1.9024 | W438: =INDEX(People!A:A,MATCH(M438,People!B:B,0)) -> Fred Suzuki | Y438: =IF(U438<0,"Zərər",IF(U438<100,"Aşağı Qazanc","Yüksək Qazanc")) -> Aşağı Qazanc
A439: =A438+1 -> 438 | B439: US-2023-111934 | C439: 45051 | D439: 45053 | E439: First Class | F439: GD-14590 | G439: Giulietta Dortch | H439: Corporate | I439: United States | J439: Arlington | K439: Virginia | L439: 22204 | M439: South | N439: OFF-BI-10004364 | O439: Office Supplies | P439: Binders | Q439: Storex Dura Pro Binders | R439: 11.88 | S439: 2 | T439: 0 | U439: 5.346 | W439: =INDEX(People!A:A,MATCH(M439,People!B:B,0)) -> Fred Suzuki | Y439: =IF(U439<0,"Zərər",IF(U439<100,"Aşağı Qazanc","Yüksək Qazanc")) -> Aşağı Qazanc
A440: =A439+1 -> 439 | B440: US-2023-111934 | C440: 45051 | D440: 45053 | E440: First Class | F440: GD-14590 | G440: Giulietta Dortch | H440: Corporate | I440: United States | J440: Arlington | K440: Virginia | L440: 22204 | M440: South | N440: OFF-PA-10000474 | O440: Office Supplies | P440: Paper | Q440: Easy-staple paper | R440: 35.44 | S440: 1 | T440: 0 | U440: 16.6568 | W440: =INDEX(People!A:A,MATCH(M440,People!B:B,0)) -> Fred Suzuki | Y440: =IF(U440<0,"Zərər",IF(U440<100,"Aşağı Qazanc","Yüksək Qazanc")) -> Aşağı Qazanc
A441: =A440+1 -> 440 | B441: US-2023-166457 | C441: 45051 | D441: 45055 | E441: Second Class | F441: PF-19120 | G441: Peter Fuller | H441: Consumer | I441: United States | J441: Richmond | K441: Kentucky | L441: 40475 | M441: South | N441: OFF-PA-10001363 | O441: Office Supplies | P441: Paper | Q441: Xerox 1933 | R441: 24.56 | S441: 2 | T441: 0 | U441: 11.5432 | W441: =INDEX(People!A:A,MATCH(M441,People!B:B,0)) -> Fred Suzuki | Y441: =IF(U441<0,"Zərər",IF(U441<100,"Aşağı Qazanc","Yüksək Qazanc")) -> Aşağı Qazanc
A442: =A441+1 -> 441 | B442: US-2023-166457 | C442: 45051 | D442: 45055 | E442: Second Class | F442: PF-19120 | G442: Peter Fuller | H442: Consumer | I442: United States | J442: Richmond | K442: Kentucky | L442: 40475 | M442: South | N442: OFF-PA-10003016 | O442: Office Supplies | P442: Paper | Q442: Adams "While You Were Out" Message Pads | R442: 9.42 | S442: 3 | T442: 0 | U442: 4.239 | W442: =INDEX(People!A:A,MATCH(M442,People!B:B,0)) -> Fred Suzuki | Y442: =IF(U442<0,"Zərər",IF(U442<100,"Aşağı Qazanc","Yüksək Qazanc")) -> Aşağı Qazanc
A443: =A442+1 -> 442 | B443: US-2023-160738 | C443: 45051 | D443: 45056 | E443: Standard Class | F443: KH-16330 | G443: Katharine Harms | H443: Corporate | I443: United States | J443: Freeport | K443: Illinois | L443: 61032 | M443: Central | N443: OFF-ST-10003442 | O443: Office Supplies | P443: Storage | Q443: Eldon Portable Mobile Manager | R443: 45.248 | S443: 2 | T443: 0.2 | U443: 3.9592 | W443: =INDEX(People!A:A,MATCH(M443,People!B:B,0)) -> Roxanne Rodriguez | Y443: =IF(U443<0,"Zərər",IF(U443<100,"Aşağı Qazanc","Yüksək Qazanc")) -> Aşağı Qazanc
... A446: =A445+1 -> 445 | B446: US-2023-154879 | C446: 45052 | D446: 45057 | E446: Standard Class | F446: SN-20710 | G446: Steve Nguyen | H446: Home Office | I446: United States | J446: Los Angeles | K446: California | L446: 90004 | M446: West | N446: OFF-LA-10004425 | O446: Office Supplies | P446: Labels | Q446: Staple-on labels | R446: 5.78 | S446: 2 | T446: 0 | U446: 2.7166 | W446: =INDEX(People!A:A,MATCH(M446,People!B:B,0)) -> Sadie Pawthorne | Y446: =IF(U446<0,"Zərər",IF(U446<100,"Aşağı Qazanc","Yüksək Qazanc")) -> Aşağı Qazanc
A447: =A446+1 -> 446 | B447: US-2023-166086 | C447: 45053 | D447: 45058 | E447: Standard Class | F447: CT-11995 | G447: Carol Triggs | H447: Consumer | I447: United States | J447: Lawrence | K447: Massachusetts | L447: 01841 | M447: East | N447: FUR-CH-10004675 | O447: Furniture | P447: Chairs | Q447: Lifetime Advantage Folding Chairs, 4/Carton | R447: 872.32 | S447: 4 | T447: 0 | U447: 244.2496 | W447: =INDEX(People!A:A,MATCH(M447,People!B:B,0)) -> Chuck Magee | Y447: =IF(U447<0,"Zərər",IF(U447<100,"Aşağı Qazanc","Yüksək Qazanc")) -> Yüksək Qazanc
A448: =A447+1 -> 447 | B448: US-2023-166086 | C448: 45053 | D448: 45058 | E448: Standard Class | F448: CT-11995 | G448: Carol Triggs | H448: Consumer | I448: United States | J448: Lawrence | K448: Massachusetts | L448: 01841 | M448: East | N448: FUR-TA-10003469 | O448: Furniture | P448: Tables | Q448: Balt Split Level Computer Training Table | R448: 194.25 | S448: 2 | T448: 0.3 | U448: -38.85 | W448: =INDEX(People!A:A,MATCH(M448,People!B:B,0)) -> Chuck Magee | Y448: =IF(U448<0,"Zərər",IF(U448<100,"Aşağı Qazanc","Yüksək Qazanc")) -> Zərər
A449: =A448+1 -> 448 | B449: US-2023-166086 | C449: 45053 | D449: 45058 | E449: Standard Class | F449: CT-11995 | G449: Carol Triggs | H449: Consumer | I449: United States | J449: Lawrence | K449: Massachusetts | L449: 01841 | M449: East | N449: OFF-AR-10002578 | O449: Office Supplies | P449: Art | Q449: Newell 335 | R449: 8.64 | S449: 3 | T449: 0 | U449: 2.5056 | W449: =INDEX(People!A:A,MATCH(M449,People!B:B,0)) -> Chuck Magee | Y449: =IF(U449<0,"Zərər",IF(U449<100,"Aşağı Qazanc","Yüksək Qazanc")) -> Aşağı Qazanc
A450: =A449+1 -> 449 | B450: US-2023-166086 | C450: 45053 | D450: 45058 | E450: Standard Class | F450: CT-11995 | G450: Carol Triggs | H450: Consumer | I450: United States | J450: Lawrence | K450: Massachusetts | L450: 01841 | M450: East | N450: OFF-BI-10001078 | O450: Office Supplies | P450: Binders | Q450: Acco PRESSTEX Data Binder with Storage Hooks, Dark Blue, 14 7/8" X 11" | R450: 16.14 | S450: 3 | T450: 0 | U450: 7.9086 | W450: =INDEX(People!A:A,MATCH(M450,People!B:B,0)) -> Chuck Magee | Y450: =IF(U450<0,"Zərər",IF(U450<100,"Aşağı Qazanc","Yüksək Qazanc")) -> Aşağı Qazanc
A451: =A450+1 -> 450 | B451: CA-2023-166086 | C451: 45053 | D451: 45058 | E451: Standard Class | F451: CT-11995 | G451: Carol Triggs | H451: Consumer | I451: Canada | J451: Toronto | K451: Ontario | L451: M3C | M451: East | N451: FUR-CH-10004675 | O451: Furniture | P451: Chairs | Q451: Lifetime Advantage Folding Chairs, 4/Carton | R451: 872.32 | S451: 4 | T451: 0 | U451: 244.2496 | W451: =INDEX(People!A:A,MATCH(M451,People!B:B,0)) -> Chuck Magee | Y451: =IF(U451<0,"Zərər",IF(U451<100,"Aşağı Qazanc","Yüksək Qazanc")) -> Yüksək Qazanc
A452: =A451+1 -> 451 | B452: CA-2023-166086 | C452: 45053 | D452: 45058 | E452: Standard Class | F452: CT-11995 | G452: Carol Triggs | H452: Consumer | I452: Canada | J452: Toronto | K452: Ontario | L452: M3C | M452: East | N452: FUR-TA-10003469 | O452: Furniture | P452: Tables | Q452: Balt Split Level Computer Training Table | R452: 194.25 | S452: 2 | T452: 0.3 | U452: -38.85 | W452: =INDEX(People!A:A,MATCH(M452,People!B:B,0)) -> Chuck Magee | Y452: =IF(U452<0,"Zərər",IF(U452<100,"Aşağı Qazanc","Yüksək Qazanc")) -> Zərər
A453: =A452+1 -> 452 | B453: CA-2023-166086 | C453: 45053 | D453: 45058 | E453: Standard Class | F453: CT-11995 | G453: Carol Triggs | H453: Consumer | I453: Canada | J453: Toronto | K453: Ontario | L453: M3C | M453: East | N453: OFF-AR-10002578 | O453: Office Supplies | P453: Art | Q453: Newell 335 | R453: 8.64 | S453: 3 | T453: 0 | U453: 2.5056 | W453: =INDEX(People!A:A,MATCH(M453,People!B:B,0)) -> Chuck Magee | Y453: =IF(U453<0,"Zərər",IF(U453<100,"Aşağı Qazanc","Yüksək Qazanc")) -> Aşağı Qazanc
A454: =A453+1 -> 453 | B454: CA-2023-166086 | C454: 45053 | D454: 45058 | E454: Standard Class | F454: CT-11995 | G454: Carol Triggs | H454: Consumer | I454: Canada | J454: Toronto | K454: Ontario | L454: M3C | M454: East | N454: OFF-BI-10001078 | O454: Office Supplies | P454: Binders | Q454: Acco PRESSTEX Data Binder with Storage Hooks, Dark Blue, 14 7/8" X 11" | R454: 16.14 | S454: 3 | T454: 0 | U454: 7.9086 | W454: =INDEX(People!A:A,MATCH(M454,People!B:B,0)) -> Chuck Magee | Y454: =IF(U454<0,"Zərər",IF(U454<100,"Aşağı Qazanc","Yüksək Qazanc")) -> Aşağı Qazanc
...

Sheet People
A1: Regional Manager | B1: Region
A2: Sadie Pawthorne | B2: West
A3: Chuck Magee | B3: East
A4: Roxanne Rodriguez | B4: Central
A5: Fred Suzuki | B5: South

Sheet Products
A1: Product ID | B1: Product Name | C1: Supplier | D1: Unit Cost | E1: Target Margin
A2: OFF-PA-10000174 | B2: Message Book, Wirebound, Four 5 1/2" X 4" Forms/Pg., 200 Dupl. Sets/Book | C2: Staples | D2: 7.5 | E2: 25%
A3: OFF-BI-10004094 | B3: GBC Standard Plastic Binding Systems Combs | C3: Office Depot | D3: 15 | E3: 26%
A4: OFF-LA-10003223 | B4: Avery 508 | C4: HP | D4: 22.5 | E4: 27%
A5: OFF-ST-10002743 | B5: SAFCO Boltless Steel Shelving | C5: Canon | D5: 30 | E5: 28%
A6: OFF-AR-10003478 | B6: Avery Hi-Liter EverBold Pen Style Fluorescent Highlighters, 4/Pack | C6: Logitech | D6: 37.5 | E6: 29%
A7: FUR-CH-10004063 | B7: Global Deluxe High-Back Manager's Chair | C7: 3M | D7: 45 | E7: 30%
A8: OFF-AR-10001662 | B8: Rogers Handheld Barrel Pencil Sharpener | C8: Avery | D8: 52.5 | E8: 31%
A9: OFF-AR-10002399 | B9: Dixon Prang Watercolor Pencils, 10-Color Set with Brush | C9: IKEA | D9: 60 | E9: 32%
A10: OFF-BI-10004632 | B10: Ibico Hi-Tech Manual Binding System | C10: Samsung | D10: 67.5 | E10: 33%
A11: OFF-FA-10001883 | B11: Alliance Super-Size Bands, Assorted Sizes | C11: Dell | D11: 75 | E11: 34%
A12: OFF-PA-10000955 | B12: Southworth 25% Cotton Granite Paper & Envelopes | C12: Staples | D12: 82.5 | E12: 35%
A13: OFF-PA-10002005 | B13: Xerox 225 | C13: Office Depot | D13: 90 | E13: 36%
... A1863: FUR-BO-10002206 | B1863: Bush Saratoga Collection 5-Shelf Bookcase, Hanover Cherry, *Special Order | C1863: Office Depot | D1863: 15 | E1863: 30%

Sheet Returns
A1: Order ID | B1: Returned
A2: US-2023-100762 | B2: Yes
A3: US-2023-100867 | B3: Yes
A4: US-2023-102652 | B4: Yes
A5: US-2023-103373 | B5: Yes
A6: US-2023-103744 | B6: Yes
A7: US-2023-103940 | B7: Yes
A8: US-2023-104829 | B8: Yes
A9: US-2023-105270 | B9: Yes
A10: US-2023-108609 | B10: Yes
A11: US-2023-108861 | B11: Yes
A12: US-2023-109918 | B12: Yes
... A297: US-2026-155999 | B297: Yes
